grid_stix/__init__.py
grid_stix/base.py
grid_stix/assets/ControlCenter.py
grid_stix/assets/DistributionLine.py
grid_stix/assets/ElectronicSecurityPerimeter.py
grid_stix/assets/Generator.py
grid_stix/assets/GridComponent.py
grid_stix/assets/OTDevice.py
grid_stix/assets/OperationalGridEntity.py
grid_stix/assets/PhysicalAsset.py
grid_stix/assets/PhysicalGridAsset.py
grid_stix/assets/PhysicalSecurityPerimeter.py
grid_stix/assets/SecurityZone.py
grid_stix/assets/Substation.py
grid_stix/assets/Supplier.py
grid_stix/assets/SupplyChainRisk.py
grid_stix/assets/Transformer.py
grid_stix/assets/TransmissionLine.py
grid_stix/assets/__init__.py
grid_stix/attack_patterns/CyberAttackPattern.py
grid_stix/attack_patterns/FirmwareAttackPattern.py
grid_stix/attack_patterns/GridAttackPattern.py
grid_stix/attack_patterns/GridMitigation.py
grid_stix/attack_patterns/ImpactType.py
grid_stix/attack_patterns/PhysicalAttackPattern.py
grid_stix/attack_patterns/ProtocolAttackPattern.py
grid_stix/attack_patterns/SocialEngineeringAttackPattern.py
grid_stix/attack_patterns/__init__.py
grid_stix/components/AdvancedMeteringNetwork.py
grid_stix/components/AmiHeadEndSystem.py
grid_stix/components/BatteryEnergyStorageSystem.py
grid_stix/components/CentralizedGenerationFacility.py
grid_stix/components/ChargingConnector.py
grid_stix/components/DerCommunicationInterface.py
grid_stix/components/DerController.py
grid_stix/components/DerDevice.py
grid_stix/components/DerFirmware.py
grid_stix/components/DerNetworkInterface.py
grid_stix/components/DerOperator.py
grid_stix/components/DerOwner.py
grid_stix/components/DerScada.py
grid_stix/components/DerSystem.py
grid_stix/components/DerUser.py
grid_stix/components/Derms.py
grid_stix/components/DistributedEnergyResource.py
grid_stix/components/DistributionAsset.py
grid_stix/components/DistributionManagementSystem.py
grid_stix/components/EdgeIntelligentDevice.py
grid_stix/components/ElectricVehicle.py
grid_stix/components/ElectricVehicleSupplyEquipment.py
grid_stix-2.6.7.dist-info/licenses/LICENSE
grid_stix-2.6.7.dist-info/licenses/NOTICE
grid_stix-2.6.7.dist-info/METADATA
grid_stix-2.6.7.dist-info/WHEEL
grid_stix-2.6.7.dist-info/top_level.txt
grid_stix-2.6.7.dist-info/RECORD
