Metadata-Version: 2.4
Name: grid-stix
Version: 2.6.7
Summary: Grid-STIX Electrical Grid Cybersecurity Ontology - STIX extension for critical infrastructure
Author: CITADEL Project
License-Expression: GPL-3.0-or-later
Project-URL: Homepage, https://github.com/argonne-citadel/grid-stix
Project-URL: Repository, https://github.com/argonne-citadel/grid-stix.git
Keywords: stix,cybersecurity,electrical-grid,critical-infrastructure,ontology,threat-intelligence
Classifier: Development Status :: 3 - Alpha
Classifier: Intended Audience :: Developers
Classifier: Intended Audience :: Science/Research
Classifier: Programming Language :: Python :: 3
Classifier: Programming Language :: Python :: 3.12
Classifier: Topic :: Security
Classifier: Topic :: Scientific/Engineering
Requires-Python: >=3.12
License-File: LICENSE
License-File: NOTICE
Requires-Dist: stix2~=3.0.1
Provides-Extra: dev
Requires-Dist: bandit>=1.8; extra == "dev"
Requires-Dist: black>=25.1; extra == "dev"
Requires-Dist: mypy>=1.17; extra == "dev"
Requires-Dist: pytest>=8.4; extra == "dev"
Requires-Dist: pytest-asyncio>=1.0; extra == "dev"
Requires-Dist: pytest-cov>=6.1; extra == "dev"
Requires-Dist: pytest-mock>=3.14; extra == "dev"
Provides-Extra: ontology
Requires-Dist: rdflib>=7.1; extra == "ontology"
Requires-Dist: owlready2>=0.48; extra == "ontology"
Requires-Dist: networkx>=3.4; extra == "ontology"
Requires-Dist: plotly>=6.1; extra == "ontology"
Requires-Dist: pygraphviz>=1.14; extra == "ontology"
Requires-Dist: scipy>=1.15; extra == "ontology"
Requires-Dist: numpy>=2.2; extra == "ontology"
Requires-Dist: jinja2>=3.1; extra == "ontology"
Dynamic: license-file
